<odoo>

    <!-- Production -->
 <!--    <record id="view_location_form" model="ir.ui.view">
        <field name="name">Stock Location</field>
        <field name="model">stock.location</field>
        <field name="inherit_id" ref="stock.view_location_form"/>
        <field name="arch" type="xml">
            <field name="comment" position="after">
                <button name="action_repair_quant_tracing" type="object" string="Repair Traceability" />
            </field>
        </field>
    </record> -->

    <!-- Production -->
    <!-- <record id="mrp_production_form_view_generate_pallet_enhance" model="ir.ui.view">
        <field name="name">mrp.production</field>
        <field name="model">mrp.production</field>
        <field name="inherit_id" ref="product_auto_lot.mrp_production_form_view_inherit_generate_pallet"/>
        <field name="arch" type="xml">
            <xpath expr="//field[@name='package_ids']/tree/field[@name='default_lot_code_id']" position="after">
                <field name="start_date"/>
                <field name="end_date"/>
            </xpath>
        </field>
    </record> -->
</odoo>